estructuraDatos/__init__.py
estructuraDatos-0.0.1.dist-info/LICENSE.txt
estructuraDatos-0.0.1.dist-info/METADATA
estructuraDatos-0.0.1.dist-info/WHEEL
estructuraDatos-0.0.1.dist-info/top_level.txt
estructuraDatos-0.0.1.dist-info/RECORD
