Metadata-Version: 2.1
Name: estructuraDatos
Version: 0.0.1
Summary: Paquete para crear estructuras de datos requeridas para la solución de problemas de búsqueda no-informada e informada.
Home-page: UNKNOWN
Author: Claudia, Juan Carlos y Taylor
Author-email: tasprillab@ucentral.edu.co
License: UNKNOWN
Platform: UNKNOWN
